py_bcndecode-0.2.0.dist-info/RECORD
py_bcndecode-0.2.0.dist-info/WHEEL
py_bcndecode-0.2.0.dist-info/top_level.txt
py_bcndecode-0.2.0.dist-info/METADATA
py_bcndecode/version.py
py_bcndecode/__init__.py
py_bcndecode/rust.abi3.so
